backend/.env
backend/__pycache__/validation.cpython-312.pyc
backend/app/__init__.py
backend/app/server.py
backend/app/__pycache__/__init__.cpython-312.pyc
backend/app/__pycache__/server.cpython-312.pyc
backend/app/static/android-chrome-192x192.png
backend/app/static/android-chrome-512x512.png
backend/app/static/apple-touch-icon.png
backend/app/static/asset-manifest.json
backend/app/static/favicon.ico
backend/app/static/icon.svg
backend/app/static/index.html
backend/app/static/logo192.png
backend/app/static/logo512.png
backend/app/static/manifest.json
backend/app/static/manifest.webmanifest
backend/app/static/robots.txt
backend/app/static/static/css/main.1b3d4f25.css
backend/app/static/static/css/main.1b3d4f25.css.map
backend/app/static/static/css/main.ea1cb791.css
backend/app/static/static/css/main.ea1cb791.css.map
backend/app/static/static/js/main.36c0c139.js
backend/app/static/static/js/main.36c0c139.js.LICENSE.txt
backend/app/static/static/js/main.36c0c139.js.map
backend/app/static/static/js/main.3979d7de.js
backend/app/static/static/js/main.3979d7de.js.LICENSE.txt
backend/app/static/static/js/main.3979d7de.js.map
backend/app/static/static/js/main.4c79c613.js
backend/app/static/static/js/main.4c79c613.js.LICENSE.txt
backend/app/static/static/js/main.4c79c613.js.map
backend/app/static/static/js/main.568bdf61.js
backend/app/static/static/js/main.568bdf61.js.LICENSE.txt
backend/app/static/static/js/main.568bdf61.js.map
backend/app/static/static/js/main.6a2e61b5.js
backend/app/static/static/js/main.6a2e61b5.js.LICENSE.txt
backend/app/static/static/js/main.6a2e61b5.js.map
backend/app/static/static/js/main.862ea425.js
backend/app/static/static/js/main.862ea425.js.LICENSE.txt
backend/app/static/static/js/main.862ea425.js.map
backend/app/static/static/js/main.8a549c05.js
backend/app/static/static/js/main.8a549c05.js.LICENSE.txt
backend/app/static/static/js/main.8a549c05.js.map
backend/app/static/static/js/main.ba801f60.js
cinder_ml-1.8.2.dist-info/licenses/LICENSE.txt
cinder_ml-1.8.2.dist-info/METADATA
cinder_ml-1.8.2.dist-info/WHEEL
cinder_ml-1.8.2.dist-info/entry_points.txt
cinder_ml-1.8.2.dist-info/top_level.txt
cinder_ml-1.8.2.dist-info/RECORD
